{
  "$schema": "http://json-schema.org/draft-07/schema#",
  "properties": {
    "affinity": {
      "required": [],
      "title": "affinity",
      "type": "object"
    },
    "fullnameOverride": {
      "default": "",
      "required": [],
      "title": "fullnameOverride",
      "type": "string"
    },
    "global": {
      "description": "Global values are values that can be accessed from any chart or subchart by exactly the same name.",
      "required": [],
      "title": "global",
      "type": "object"
    },
    "image": {
      "properties": {
        "pullPolicy": {
          "required": [],
          "type": "object"
        },
        "repository": {
          "required": [],
          "type": "object"
        },
        "tag": {
          "required": [],
          "type": "object"
        }
      },
      "required": [],
      "title": "image",
      "type": "object"
    },
    "imagePullSecrets": {
      "items": {
        "required": []
      },
      "required": [],
      "title": "imagePullSecrets",
      "type": "array"
    },
    "ingress": {
      "properties": {
        "annotations": {
          "required": [],
          "type": "object"
        },
        "className": {
          "required": [],
          "type": "object"
        },
        "enabled": {
          "required": [],
          "type": "object"
        },
        "hosts": {
          "required": [],
          "type": "object"
        },
        "tls": {
          "required": [],
          "type": "object"
        }
      },
      "required": [],
      "title": "ingress",
      "type": "object"
    },
    "livenessProbe": {
      "properties": {
        "httpGet": {
          "properties": {
            "path": {
              "default": "/",
              "required": [],
              "title": "path",
              "type": "string"
            },
            "port": {
              "default": "http",
              "required": [],
              "title": "port",
              "type": "string"
            }
          },
          "required": [],
          "type": "object"
        }
      },
      "required": [],
      "title": "livenessProbe",
      "type": "object"
    },
    "nameOverride": {
      "default": "",
      "required": [],
      "title": "nameOverride",
      "type": "string"
    },
    "nodeSelector": {
      "required": [],
      "title": "nodeSelector",
      "type": "object"
    },
    "persistence": {
      "description": "Persistence is required if you are using the SQLite database (default).",
      "properties": {
        "accessMode": {
          "required": [],
          "type": "object"
        },
        "enabled": {
          "required": [],
          "type": "object"
        },
        "size": {
          "required": [],
          "type": "object"
        }
      },
      "required": [],
      "title": "persistence",
      "type": "object"
    },
    "podAnnotations": {
      "required": [],
      "title": "podAnnotations",
      "type": "object"
    },
    "podLabels": {
      "required": [],
      "title": "podLabels",
      "type": "object"
    },
    "podSecurityContext": {
      "required": [],
      "title": "podSecurityContext",
      "type": "object"
    },
    "readinessProbe": {
      "properties": {
        "httpGet": {
          "properties": {
            "path": {
              "default": "/",
              "required": [],
              "title": "path",
              "type": "string"
            },
            "port": {
              "default": "http",
              "required": [],
              "title": "port",
              "type": "string"
            }
          },
          "required": [],
          "type": "object"
        }
      },
      "required": [],
      "title": "readinessProbe",
      "type": "object"
    },
    "replicaCount": {
      "default": 1,
      "description": "Number of replicas to run. \u003e1 requires RWX persistence",
      "required": [],
      "title": "replicaCount",
      "type": "integer"
    },
    "resources": {
      "required": [],
      "title": "resources",
      "type": "object"
    },
    "securityContext": {
      "required": [],
      "title": "securityContext",
      "type": "object"
    },
    "service": {
      "properties": {
        "port": {
          "required": [],
          "type": "object"
        },
        "type": {
          "required": [],
          "type": "object"
        }
      },
      "required": [],
      "title": "service",
      "type": "object"
    },
    "serviceAccount": {
      "properties": {
        "annotations": {
          "required": [],
          "type": "object"
        },
        "automount": {
          "required": [],
          "type": "object"
        },
        "create": {
          "required": [],
          "type": "object"
        },
        "name": {
          "required": [],
          "type": "object"
        }
      },
      "required": [],
      "title": "serviceAccount",
      "type": "object"
    },
    "strategy": {
      "properties": {
        "type": {
          "required": [],
          "type": "object"
        }
      },
      "required": [],
      "title": "strategy",
      "type": "object"
    },
    "tolerations": {
      "items": {
        "required": []
      },
      "required": [],
      "title": "tolerations",
      "type": "array"
    }
  },
  "required": [],
  "type": "object"
}